scenext_mcp/__init__.py
scenext_mcp/_version.py
scenext_mcp/server.py
scenext_mcp-1.2.4.dist-info/licenses/LICENSE
scenext_mcp-1.2.4.dist-info/METADATA
scenext_mcp-1.2.4.dist-info/WHEEL
scenext_mcp-1.2.4.dist-info/entry_points.txt
scenext_mcp-1.2.4.dist-info/top_level.txt
scenext_mcp-1.2.4.dist-info/RECORD
