Metadata-Version: 2.4
Name: scenext-mcp
Version: 1.2.4
Summary: Scenext MCP Server - AI视频生成服务的MCP服务器
Author-email: Scenext <support@lynkframe.com>
License-Expression: MIT
Project-URL: Homepage, https://github.com/typing233/scenext-mcp
Project-URL: Repository, https://github.com/typing233/scenext-mcp
Project-URL: Documentation, https://github.com/typing233/scenext-mcp
Project-URL: Bug Reports, https://github.com/typing233/scenext-mcp/issues
Keywords: mcp,model-context-protocol,ai,video,generation,scenext
Classifier: Development Status :: 4 - Beta
Classifier: Intended Audience :: Developers
Classifier: Operating System :: OS Independent
Classifier: Programming Language :: Python :: 3.10
Classifier: Programming Language :: Python :: 3.11
Classifier: Programming Language :: Python :: 3.12
Classifier: Topic :: Software Development :: Libraries :: Python Modules
Classifier: Topic :: Internet :: WWW/HTTP :: HTTP Servers
Classifier: Topic :: Multimedia :: Video
Requires-Python: >=3.10
License-File: LICENSE
Requires-Dist: fastmcp>=2.6.1
Requires-Dist: aiohttp>=3.12.6
Requires-Dist: python-dotenv>=1.0.0
Dynamic: license-file
